datview/__init__.py
datview/main.py
datview/assets/__init__.py
datview/assets/datview_icon.png
datview/lib/__init__.py
datview/lib/interactions.py
datview/lib/rendering.py
datview/lib/utilities.py
datview-1.4.0.dist-info/licenses/LICENSE
datview-1.4.0.dist-info/METADATA
datview-1.4.0.dist-info/WHEEL
datview-1.4.0.dist-info/entry_points.txt
datview-1.4.0.dist-info/top_level.txt
datview-1.4.0.dist-info/RECORD
