Metadata-Version: 2.4
Name: datview
Version: 1.4.0
Summary: GUI software for viewing images, text, cine, and HDF files.
Home-page: https://github.com/algotom/datview
Download-URL: https://github.com/algotom/datview.git
Author: Nghia Vo
Author-email: nvo@bnl.gov
License: Apache 2.0
Keywords: HDF Viewer,CINE viewer,NXS Viewer,Image viewer,Data viewer
Platform: Any
Classifier: Programming Language :: Python :: 3
Classifier: License :: OSI Approved :: Apache Software License
Classifier: Intended Audience :: Science/Research
Classifier: Operating System :: OS Independent
Classifier: Natural Language :: English
Classifier: Topic :: Scientific/Engineering
Requires-Python: >=3.9
License-File: LICENSE
Requires-Dist: h5py
Requires-Dist: hdf5plugin
Requires-Dist: pillow
Requires-Dist: matplotlib
Dynamic: author
Dynamic: author-email
Dynamic: classifier
Dynamic: description
Dynamic: description-content-type
Dynamic: download-url
Dynamic: home-page
Dynamic: keywords
Dynamic: license
Dynamic: license-file
Dynamic: platform
Dynamic: requires-dist
Dynamic: requires-python
Dynamic: summary
